common/__init__.py
common/common_rest_util.py
common/csv_util.py
common/date_time_util.py
common/ecs_util.py
common/encoding_util.py
common/enum_util.py
common/enums.py
common/excel_util.py
common/external_rest_service.py
common/file_reader.py
common/file_util.py
common/filters.py
common/geo_location_util.py
common/html_util.py
common/internal_rest_service.py
common/json_util.py
common/list_util.py
common/map_util.py
common/model_util.py
common/mysql_util.py
common/numbers_util.py
common/pandas_util.py
common/pdf_util.py
common/random_util.py
common/response_util.py
common/s3_client_util.py
common/s3_file_util.py
common/service_util.py
common/sqs_client_util.py
common/sqs_util.py
common/str_regex_util.py
common/string_util.py
common/template_util.py
common/thread_pool_util.py
common/transformers.py
common/uuid_util.py
common/validators.py
common/video_util.py
data_purging_framework/__init__.py
data_purging_framework/data_purging_process.py
data_purging_framework/interval_type_process.py
codejudge_common_utils-0.1.dist-info/METADATA
codejudge_common_utils-0.1.dist-info/WHEEL
codejudge_common_utils-0.1.dist-info/top_level.txt
codejudge_common_utils-0.1.dist-info/RECORD
